easyimap/__init__.py
easyimap/easyimap.py
easyimap-0.7.0.dist-info/LICENSE.txt
easyimap-0.7.0.dist-info/METADATA
easyimap-0.7.0.dist-info/WHEEL
easyimap-0.7.0.dist-info/top_level.txt
easyimap-0.7.0.dist-info/RECORD
